stellar_sdk/__init__.py
stellar_sdk/__version__.py
stellar_sdk/account.py
stellar_sdk/address.py
stellar_sdk/asset.py
stellar_sdk/auth.py
stellar_sdk/base_server.py
stellar_sdk/base_soroban_server.py
stellar_sdk/base_transaction_envelope.py
stellar_sdk/decorated_signature.py
stellar_sdk/exceptions.py
stellar_sdk/fee_bump_transaction.py
stellar_sdk/fee_bump_transaction_envelope.py
stellar_sdk/helpers.py
stellar_sdk/keypair.py
stellar_sdk/ledger_bounds.py
stellar_sdk/liquidity_pool_asset.py
stellar_sdk/liquidity_pool_id.py
stellar_sdk/memo.py
stellar_sdk/muxed_account.py
stellar_sdk/network.py
stellar_sdk/preconditions.py
stellar_sdk/price.py
stellar_sdk/py.typed
stellar_sdk/scval.py
stellar_sdk/server.py
stellar_sdk/server_async.py
stellar_sdk/signer.py
stellar_sdk/signer_key.py
stellar_sdk/soroban_data_builder.py
stellar_sdk/soroban_rpc.py
stellar_sdk/soroban_server.py
stellar_sdk/soroban_server_async.py
stellar_sdk/strkey.py
stellar_sdk/time_bounds.py
stellar_sdk/transaction.py
stellar_sdk/transaction_builder.py
stellar_sdk/transaction_envelope.py
stellar_sdk/utils.py
stellar_sdk/call_builder/__init__.py
stellar_sdk/call_builder/base/__init__.py
stellar_sdk/call_builder/base/base_accounts_call_builder.py
stellar_sdk/call_builder/base/base_assets_call_builder.py
stellar_sdk/call_builder/base/base_call_builder.py
stellar_sdk/call_builder/base/base_claimable_balances_call_builder.py
stellar_sdk/call_builder/base/base_data_call_builder.py
stellar_sdk/call_builder/base/base_effects_call_builder.py
stellar_sdk/call_builder/base/base_fee_stats_call_builder.py
stellar_sdk/call_builder/base/base_ledgers_call_builder.py
stellar_sdk/call_builder/base/base_liquidity_pools_builder.py
stellar_sdk/call_builder/base/base_offers_call_builder.py
stellar_sdk/call_builder/base/base_operations_call_builder.py
stellar_sdk/call_builder/base/base_orderbook_call_builder.py
stellar_sdk/call_builder/base/base_payments_call_builder.py
stellar_sdk/call_builder/base/base_root_call_builder.py
stellar_sdk-13.2.1.dist-info/licenses/LICENSE
stellar_sdk-13.2.1.dist-info/WHEEL
stellar_sdk-13.2.1.dist-info/METADATA
stellar_sdk-13.2.1.dist-info/RECORD
