Metadata-Version: 2.4
Name: stellar-sdk
Version: 13.2.1
Summary: The Python Stellar SDK library provides APIs to build transactions and connect to Horizon and Stellar RPC server.
Keywords: stellar-sdk,stellar,stellar.org,lumens,xlm,blockchain,distributed exchange,cryptocurrency,dex,horizon,soroban,sdex,trading,soroban,soroban-rpc,stellar-rpc
Author-email: overcat <4catcode@gmail.com>, Eno <appweb.cn@gmail.com>
Maintainer-email: overcat <4catcode@gmail.com>
Requires-Python: >=3.10,<4.0
License-Expression: Apache-2.0
Classifier: Development Status :: 5 - Production/Stable
Classifier: Intended Audience :: Developers
Classifier: Natural Language :: English
Classifier: Operating System :: OS Independent
Classifier: Programming Language :: Python
Classifier: Programming Language :: Python :: 3 :: Only
Classifier: Programming Language :: Python :: Implementation :: CPython
Classifier: Programming Language :: Python :: Implementation :: PyPy
Classifier: Topic :: Software Development :: Libraries :: Python Modules
Classifier: Typing :: Typed
License-File: LICENSE
Requires-Dist: mnemonic>=0.20
Requires-Dist: pydantic>=2.0.0
Requires-Dist: pynacl>=1.4.0
Requires-Dist: requests>=2.0.0
Requires-Dist: requests-sse>=0.3
Requires-Dist: toml>=0.10.2; python_version < '3.11'
Requires-Dist: typing-extensions>=4.0.0
Requires-Dist: xdrlib3>=0.1.1
Requires-Dist: aiohttp>=3.9.1 ; extra == "aiohttp"
Requires-Dist: aiohttp-sse-client>=0.2.1 ; extra == "aiohttp"
Requires-Dist: shamir-mnemonic>=0.3.0 ; extra == "shamir"
Project-URL: Bug Tracker, https://github.com/StellarCN/py-stellar-base/issues
Project-URL: Changelog, https://github.com/StellarCN/py-stellar-base/blob/main/CHANGELOG.md
Project-URL: Documentation, https://stellar-sdk.readthedocs.io/
Project-URL: Homepage, https://github.com/StellarCN/py-stellar-base
Project-URL: Issues, https://github.com/StellarCN/py-stellar-base/issues
Project-URL: Repository, https://github.com/StellarCN/py-stellar-base
Provides-Extra: aiohttp
Provides-Extra: shamir
